aslabs/near/__init__.py
aslabs/near/account.py
aslabs/near/config.py
aslabs/near/nft/__init__.py
aslabs/near/nft/models.py
aslabs/near/nft/near_nft.py
aslabs/near/signature_verifier/__init__.py
aslabs/near/signature_verifier/models.py
aslabs/near/signature_verifier/signature_verifier.py
aslabs/near/signature_verifier/signature_verifier_abc.py
aslabs/near/signer.py
aslabs_near-0.0.5.dist-info/WHEEL
aslabs_near-0.0.5.dist-info/METADATA
aslabs_near-0.0.5.dist-info/RECORD
