Metadata-Version: 2.1
Name: aslabs-near
Version: 0.0.5
Summary: 
Author: Titusz Ban
Author-email: tituszban@antisociallabs.io
Requires-Python: >=3.9,<4.0
Classifier: Programming Language :: Python :: 3
Classifier: Programming Language :: Python :: 3.9
Classifier: Programming Language :: Python :: 3.10
Classifier: Programming Language :: Python :: 3.11
Requires-Dist: aslabs-utils
Requires-Dist: base58 (>=2.1.1,<3.0.0)
Requires-Dist: ed25519 (>=1.5,<2.0)
Requires-Dist: near-api-py (>=0.1.0,<0.2.0)
Requires-Dist: python-dateutil (>=2.8.2,<3.0.0)
